{
  "data": [
    {
      "first": "Vishal",
      "last": "Hariyani",
      "address": "Asihwariyam Humara pune",
      "email": "vishalhariyani5@gmail.com",
      "contact": "83902999467",
      "id": "ef02"
    },
    {
      "id": "ec90",
      "first": "Vishal",
      "last": "Hariyani",
      "address": "Aishwariyam Humara pune Chikhali",
      "email": "vishalhariyani5@gmail.com",
      "contact": "8390299946"
    },
    {
      "first": "Vishal",
      "last": "Hariyani",
      "address": "Aishwariyam Humara ",
      "email": "vishalhariyani5@gmail.com",
      "contact": "8746543236",
      "id": "fdf9"
    }
  ]
}